Metadata-Version: 2.1
Name: python-dashtx
Version: 0.1.1
Summary: Dash module for use with python-bitcointx
Home-page: https://github.com/zebra-lucky/python-dashtx
License: UNKNOWN
Platform: UNKNOWN
Classifier: Programming Language :: Python :: 3.6
Classifier: Programming Language :: Python :: 3.7
Classifier: Programming Language :: Python :: 3.8
Classifier: License :: OSI Approved :: GNU Lesser General Public License v3 or later (LGPLv3+)
Requires-Python: >=3.6
License-File: LICENSE
